bag/__init__.py
bag/bag_main.py
bag/bag_ops.py
bagSync/bagit.py
bagSync/bag/__init__.py
bagSync/bag/bag_main.py
bagSync/bag/bag_ops.py
bagSync/bin/bagit.py
bdrc_bag-0.0.7.dist-info/LICENSE
bdrc_bag-0.0.7.dist-info/METADATA
bdrc_bag-0.0.7.dist-info/WHEEL
bdrc_bag-0.0.7.dist-info/entry_points.txt
bdrc_bag-0.0.7.dist-info/top_level.txt
bdrc_bag-0.0.7.dist-info/RECORD
