Metadata-Version: 2.1
Name: bdrc-bag
Version: 0.0.7
Summary: Create and extract BDRC bags
Author-email: Jim Katz <jim@tbrc.org>
Classifier: Programming Language :: Python :: 3
Classifier: License :: OSI Approved :: GNU General Public License v3 (GPLv3)
Classifier: Operating System :: OS Independent
Requires-Python: >=3.8
License-File: LICENSE
Requires-Dist: bagit
